packages/__init__.py
packages/tikup.py
tikup/__init__.py
tikup/argparser.py
tikup/tikup.py
tikup-2021.8.24.dist-info/LICENSE
tikup-2021.8.24.dist-info/METADATA
tikup-2021.8.24.dist-info/WHEEL
tikup-2021.8.24.dist-info/entry_points.txt
tikup-2021.8.24.dist-info/top_level.txt
tikup-2021.8.24.dist-info/RECORD
