Metadata-Version: 2.1
Name: tikup
Version: 2021.8.24
Summary: An auto downloader and uploader for TikTok videos.
Home-page: https://github.com/Coloradohusky/TikUp
Author: Coloradohusky
License: UNKNOWN
Platform: UNKNOWN
Requires-Python: >=3.5, <4
License-File: LICENSE
Requires-Dist: internetarchive (>=2.0.3)
Requires-Dist: TikTokApi (>=3.9.9)
Requires-Dist: youtube-dl (>=2021.6.6)
Requires-Dist: playwright (>=1.9.2)
